Metadata-Version: 2.1
Name: django-makesuperuser
Version: 2020.7.1
Summary: manage.py makesuperuser --username admin --password admin
Home-page: https://github.com/andrewp-as-is/django-makesuperuser.py
License: Unlicense
Keywords: django superuser
Platform: UNKNOWN
Classifier: Framework :: Django
Classifier: License :: Public Domain
Classifier: Operating System :: OS Independent
Classifier: Programming Language :: Python :: 3
